{
  "MRData": {
    "xmlns": "http:\/\/ergast.com\/mrd\/1.5",
    "series": "f1",
    "url": "http://ergast.com/api/f1/2023.json",
    "limit": "30",
    "offset": "0",
    "total": "22",
    "RaceTable": {
      "season": "2023",
      "Races": [
        {
          "season": "2023",
          "round": "1",
          "url": "https://es.wikipedia.org/wiki/Gran_Premio_de_Bar%C3%A9in",
          "raceName": "Bahrain Grand Prix",
          "Circuit": {
            "circuitId": "bahrain",
            "url": "https://es.wikipedia.org/wiki/Circuito_Internacional_de_Bar%C3%A9in",
            "circuitName": "Bahrain International Circuit",
            "Location": {
              "locality": "Sakhir",
              "country": "Bahrain"
            },
            "Values": {
              "price1": "200",
              "price2": "300",
              "price3": "500"
            }
          }
        },
        {
          "season": "2023",
          "round": "2",
          "url": "https://es.wikipedia.org/wiki/Gran_Premio_de_Arabia_Saudita",
          "raceName": "Saudi Arabian Grand Prix",
          "Circuit": {
            "circuitId": "jeddah",
            "url": "https://es.wikipedia.org/wiki/Circuito_de_la_Corniche_de_Yeda",
            "circuitName": "Jeddah Corniche Circuit",
            "Location": {
              "locality": "Jeddah",
              "country": "Arabia Saudita"
            }            
          },
          "Values": {
            "price1": "200",
            "price2": "300",
            "price3": "500"
          }
        },
        {
          "season": "2023",
          "round": "3",
          "url": "https:\/\/en.wikipedia.org\/wiki\/2023_Australian_Grand_Prix",
          "raceName": "Australian Grand Prix",
          "Circuit": {
            "circuitId": "albert_park",
            "url": "http:\/\/en.wikipedia.org\/wiki\/Melbourne_Grand_Prix_Circuit",
            "circuitName": "Albert Park Grand Prix Circuit",
            "Location": {
              "locality": "Melbourne",
              "country": "Australia"
            }            
          },
          "Values": {
            "price1": "200",
            "price2": "300",
            "price3": "500"
          }
        },
        {
          "season": "2023",
          "round": "4",
          "url": "https://es.wikipedia.org/wiki/Gran_Premio_de_Australia",
          "raceName": "Azerbaijan Grand Prix",
          "Circuit": {
            "circuitId": "baku",
            "url": "https://es.wikipedia.org/wiki/Circuito_de_Albert_Park",
            "circuitName": "Baku City Circuit",
            "Location": {
              "locality": "Baku",
              "country": "Azerbaijan"
            },
            "Values": {
              "price1": "200",
              "price2": "300",
              "price3": "500"
            }
          }
        },
        {
          "season": "2023",
          "round": "5",
          "url": "https://es.wikipedia.org/wiki/Aut%C3%B3dromo_Internacional_de_Miami",
          "raceName": "Miami Grand Prix",
          "Circuit": {
            "circuitId": "miami",
            "url": "https://es.wikipedia.org/wiki/Circuito_callejero_de_Bak%C3%BA",
            "circuitName": "Miami International Autodrome",
            "Location": {
              "locality": "Miami",
              "country": "USA / Miami"
            },
            "Values": {
              "price1": "200",
              "price2": "300",
              "price3": "500"
            }
          }
        },
        {
          "season": "2023",
          "round": "6",
          "url": "https://es.wikipedia.org/wiki/Gran_Premio_de_M%C3%B3naco",
          "raceName": "Monaco Grand Prix",
          "Circuit": {
            "circuitId": "monaco",
            "url": "https://es.wikipedia.org/wiki/Circuito_de_M%C3%B3naco",
            "circuitName": "Circuit de Monaco",
            "Location": {
              "locality": "Monte-Carlo",
              "country": "Mónaco"
            },
            "Values": {
              "price1": "200",
              "price2": "300",
              "price3": "500"
            }
          }
        },
        {
          "season": "2023",
          "round": "7",
          "url": "https://es.wikipedia.org/wiki/Gran_Premio_de_Espa%C3%B1a",
          "raceName": "Spanish Grand Prix",
          "Circuit": {
            "circuitId": "catalunya",
            "url": "https://es.wikipedia.org/wiki/Circuito_de_Barcelona-Catalu%C3%B1a",
            "circuitName": "Circuit de Barcelona-Catalunya",
            "Location": {
              "locality": "Montmeló",
              "country": "España"
            },
            "Values": {
              "price1": "200",
              "price2": "300",
              "price3": "500"
            }
          }
        },
        {
          "season": "2023",
          "round": "8",
          "url": "https://es.wikipedia.org/wiki/Gran_Premio_de_Canad%C3%A1",
          "raceName": "Canadian Grand Prix",
          "Circuit": {
            "circuitId": "villeneuve",
            "url": "https://es.wikipedia.org/wiki/Circuito_Gilles_Villeneuve",
            "circuitName": "Circuit Gilles Villeneuve",
            "Location": {
              "locality": "Montreal",
              "country": "Canadá"
            },
            "Values": {
              "price1": "200",
              "price2": "300",
              "price3": "500"
            }
          }
        },
        {
          "season": "2023",
          "round": "9",
          "url": "https://es.wikipedia.org/wiki/Gran_Premio_de_Austria",
          "raceName": "Austrian Grand Prix",
          "Circuit": {
            "circuitId": "red_bull_ring",
            "url": "https://es.wikipedia.org/wiki/Red_Bull_Ring",
            "circuitName": "Red Bull Ring",
            "Location": {
              "locality": "Spielberg",
              "country": "Austria"
            },
            "Values": {
              "price1": "200",
              "price2": "300",
              "price3": "500"
            }
          }
        },
        {
          "season": "2023",
          "round": "10",
          "url": "https://es.wikipedia.org/wiki/Gran_Premio_de_Gran_Breta%C3%B1a",
          "raceName": "British Grand Prix",
          "Circuit": {
            "circuitId": "silverstone",
            "url": "https://es.wikipedia.org/wiki/Circuito_de_Silverstone",
            "circuitName": "Silverstone Circuit",
            "Location": {
              "locality": "Silverstone",
              "country": "Reino Unido"
            },
            "Values": {
              "price1": "200",
              "price2": "300",
              "price3": "500"
            }
          }
        },
        {
          "season": "2023",
          "round": "11",
          "url": "https://es.wikipedia.org/wiki/Gran_Premio_de_Hungr%C3%ADa",
          "raceName": "Hungarian Grand Prix",
          "Circuit": {
            "circuitId": "hungaroring",
            "url": "https://es.wikipedia.org/wiki/Hungaroring",
            "circuitName": "Hungaroring",
            "Location": {
              "locality": "Budapest",
              "country": "Hungría"
            },
            "Values": {
              "price1": "200",
              "price2": "300",
              "price3": "500"
            }
          }
        },
        {
          "season": "2023",
          "round": "12",
          "url": "https://es.wikipedia.org/wiki/Gran_Premio_de_B%C3%A9lgica",
          "raceName": "Belgian Grand Prix",
          "Circuit": {
            "circuitId": "spa",
            "url": "https://es.wikipedia.org/wiki/Circuito_de_Spa-Francorchamps",
            "circuitName": "Circuit de Spa-Francorchamps",
            "Location": {
              "locality": "Spa",
              "country": "Bélgica"
            },
            "Values": {
              "price1": "200",
              "price2": "300",
              "price3": "500"
            }
          }
        },
        {
          "season": "2023",
          "round": "13",
          "url": "https://es.wikipedia.org/wiki/Gran_Premio_de_los_Pa%C3%ADses_Bajos",
          "raceName": "Dutch Grand Prix",
          "Circuit": {
            "circuitId": "zandvoort",
            "url": "https://es.wikipedia.org/wiki/Circuito_de_Zandvoort",
            "circuitName": "Circuit Park Zandvoort",
            "Location": {
              "locality": "Zandvoort",
              "country": "Países Bajos"
            },
            "Values": {
              "tribuna1": "Tribuna Arena 1 - Sáb & Dom",
              "price1": "635,00",
              "img1": "https://static.tickets-platform.com/cinematic/slideshow/42247/grandstands/11307/91fc76b366d362984062af7398b9fc89.jpg",
              "tribuna2": "Tribuna Eastside 3 - Sáb & Dom",
              "price2": "635,00",
              "img2": "https://static.tickets-platform.com/cinematic/slideshow/42247/grandstands/11397/75d8df42de46960d320929dfc0cd93af.jpg",
              "tribuna3": "Ben Pon 1 - Vie, Sáb & Dom",
              "price3": "685,00",
              "img3": "https://static.tickets-platform.com/cinematic/slideshow/42247/grandstands/20357/8b2c8c522af16dae8b09eb4113931606.jpg"
            }
          }
        },
        {
          "season": "2023",
          "round": "14",
          "url": "https://es.wikipedia.org/wiki/Gran_Premio_de_Italia",
          "raceName": "Italian Grand Prix",
          "Circuit": {
            "circuitId": "monza",
            "url": "https://es.wikipedia.org/wiki/Autodromo_Nazionale_di_Monza",
            "circuitName": "Autodromo Nazionale di Monza",
            "Location": {
              "locality": "Monza",
              "country": "Italia"
            },
            "Values": {
              "tribuna1": "(6b) Alta Velocita B - Vie, Sáb & Dom",
              "price1": "650",
              "img1": "https://static.tickets-platform.com/cinematic/slideshow/51397/grandstands/8665/1872993057d1e649ae6722cfe0c632fd.jpg",
              "tribuna2": "(1) Centrale - Vie, Sáb & Dom",
              "price2": "1250",
              "img2": "https://static.tickets-platform.com/cinematic/slideshow/51397/grandstands/8615/49d1b8ca5f15b258b45e8bbd4da57745.jpg",
              "tribuna3": "(16) Ascari - Vie, Sáb & Dom",
              "price3": "875",
              "img3": "https://static.tickets-platform.com/cinematic/slideshow/42247/grandstands/20357/8b2c8c522af16dae8b09eb4113931606.jpg"
            }
          }
        },
        {
          "season": "2023",
          "round": "15",
          "url": "https://es.wikipedia.org/wiki/Gran_Premio_de_Singapur",
          "raceName": "Singapore Grand Prix",
          "Circuit": {
            "circuitId": "marina_bay",
            "url": "https://es.wikipedia.org/wiki/Circuito_callejero_de_Marina_Bay",
            "circuitName": "Marina Bay Street Circuit",
            "Location": {
              "locality": "Marina Bay",
              "country": "Singapur"
            },
            "Values": {
             "tribuna1": "Pit Exit Grandstand - Vie, Sab & Dom",
              "price1": "980",
              "img1": "https://static.tickets-platform.com/cinematic/slideshow/51367/grandstands/20657/7e42ee4aac6753b8483b4bf86e4648ac.jpg",
              "tribuna2": "Tribuna Pit - Front Rows - Vie, Sab & Dom",
              "price2": "990",
              "img2": "https://static.tickets-platform.com/cinematic/slideshow/51367/grandstands/20367/53ee9a3649cfe69d66badcd34eb9e42a.jpg",
              "tribuna3": "Promenade - Vie, Sab & Dom",
              "price3": "840",
              "img3": "https://static.tickets-platform.com/cinematic/slideshow/51367/grandstands/20707/8d375f338cb11c879ab6fb6fb5866ae4.jpg"
            }
          }
        },
        {
          "season": "2023",
          "round": "16",
          "url": "https://es.wikipedia.org/wiki/Gran_Premio_de_Jap%C3%B3n",
          "raceName": "Japanese Grand Prix",
          "Circuit": {
            "circuitId": "suzuka",
            "url": "https://es.wikipedia.org/wiki/Circuito_de_Suzuka",
            "circuitName": "Suzuka Circuit",
            "Location": {
              "locality": "Suzuka",
              "country": "Japón"
            },
            "Values": {
              "tribuna1": "Tribuna G - Overpass - Vie, Sáb & Dom",
              "price1": "650",
              "img1": "https://static.tickets-platform.com/cinematic/slideshow/2814/grandstands/20537/1a6215b0a31158d4668e04d3c1159447.jpg",
              "tribuna2": "Tribuna O - Temporary Stand - Vie, Sáb & Dom",
              "price2": "750",
              "img2": "https://static.tickets-platform.com/cinematic/slideshow/2814/grandstands/20557/a9b47628d323fd75cef10699f7caaf67.jpg",
              "tribuna3": "West Area - L, M, N, P - Asiento libre - Vie, Sáb & Dom",
              "price3": "350",
              "img3": "https://static.tickets-platform.com/cinematic/slideshow/2814/grandstands/11004/66055ec38894d06aad4c00f8350d277e.jpg"
            }
          }
        },
        {
          "season": "2023",
          "round": "17",
          "url": "https://es.wikipedia.org/wiki/Gran_Premio_de_Catar",
          "raceName": "Qatar Grand Prix",
          "Circuit": {
            "circuitId": "losail",
            "url": "https://es.wikipedia.org/wiki/Circuito_Internacional_de_Losail",
            "circuitName": "Losail International Circuit",
            "Location": {
              "locality": "Al Daayen",
              "country": "Qatar"
            },
            "Values": {
             "tribuna1": "Lusail Lounge add-on - Vie, Sáb & Dom",
              "price1": "690",
              "img1": "https://static.tickets-platform.com/cinematic/slideshow/56277/grandstands/20838/7d24a6059701c9ec5fe8765e2440bb06.jpg",
              "tribuna2": "Tribuna Principal - Vie, Sáb & Dom",
              "price2": "580",
              "img2": "https://static.tickets-platform.com/cinematic/slideshow/56277/grandstands/16887/8d7637bd3af06f0407fd691dd6b67318.jpg",
              "tribuna3": "Tribuna T2 - Vie, Sáb & Dom",
              "price3": "350",
              "img3": "https://static.tickets-platform.com/cinematic/slideshow/56277/grandstands/20747/6831126523566dae85fc0d245588d7e8.jpg"
            }
          }
        },
        {
          "season": "2023",
          "round": "18",
          "url": "https://es.wikipedia.org/wiki/Gran_Premio_de_los_Estados_Unidos",
          "raceName": "United States Grand Prix",
          "Circuit": {
            "circuitId": "americas",
            "url": "https://es.wikipedia.org/wiki/Circuito_de_las_Am%C3%A9ricas",
            "circuitName": "Circuit of the Americas",
            "Location": {
              "locality": "Austin",
              "country": "USA / Austin"
            },
            "Values": {
              "tribuna1": "Tribuna Turn 1 - Baja - Vie, Sáb & Dom",
              "price1": "900",
              "img1": "https://static.tickets-platform.com/cinematic/slideshow/2902/grandstands/10495/50d2bf4b7f56ffe333f796c26495a3f8.jpg",
              "tribuna2": "Tribuna Turn 4 - Baja - Vie, Sáb & Dom",
              "price2": "800",
              "img2": "https://static.tickets-platform.com/cinematic/slideshow/2902/grandstands/10535/2f6b2451a4ae7f06ad74c11e91367cd4.jpg",
              "tribuna3": "Tribuna Turn 6 - Alta - Vie, Sáb & Dom",
              "price3": "650",
              "img3": "https://static.tickets-platform.com/cinematic/slideshow/2902/grandstands/18687/5af0452a64c8421774af7288ebad7f26.jpg"
            }
          }
        },
        {
          "season": "2023",
          "round": "19",
          "url": "https://es.wikipedia.org/wiki/Gran_Premio_de_M%C3%A9xico",
          "raceName": "Mexico City Grand Prix",
          "Circuit": {
            "circuitId": "rodriguez",
            "url": "https://es.wikipedia.org/wiki/Aut%C3%B3dromo_Hermanos_Rodr%C3%ADguez",
            "circuitName": "Autódromo Hermanos Rodríguez",
            "Location": {
              "locality": "Mexico City",
              "country": "México"
            },
            "Values": {
              "tribuna1": "Tribuna Principal + Speed Lounge Package - Vie, Sáb & Dom",
              "price1": "1200",
              "img1": "https://static.tickets-platform.com/cinematic/slideshow/4911/grandstands/10175/432ab43a447338202d8e16c6ab6c8b73.jpg",
              "tribuna2": "Tribuna Principal - Vie, Sáb & Dom",
              "price2": "900",
              "img2": "https://static.tickets-platform.com/cinematic/slideshow/4911/grandstands/10175/f16f6f4746e589759c1390eecb55141b.jpg",
              "tribuna3": "Zona Verde - Vie, Sáb & Dom",
              "price3": "650",
              "img3": "https://static.tickets-platform.com/cinematic/slideshow/4911/grandstands/10175/06238b57c36301851bb10027d8934f65.jpg"
            }
          }
        },
        {
          "season": "2023",
          "round": "20",
            "url": "https://es.wikipedia.org/wiki/Gran_Premio_de_Brasil",
          "raceName": "São Paulo Grand Prix",
          "Circuit": {
            "circuitId": "interlagos",
            "url": "https://es.wikipedia.org/wiki/Aut%C3%B3dromo_Jos%C3%A9_Carlos_Pace",
            "circuitName": "Autódromo José Carlos Pace",
            "Location": {
              "locality": "São Paulo",
              "country": "Brasil"
            },
            "Values": {
              "tribuna1": "Orange Tree Club - Vie, Sáb & Dom",
              "price1": "1200",
              "img1": "https://static.tickets-platform.com/cinematic/slideshow/2907/grandstands/12007/d9a481376993843f4ffe7cc5dd3127f7.jpg",
              "tribuna2": "Tribuna H - Vie, Sáb & Dom",
              "price2": "900",
              "img2": "https://static.tickets-platform.com/cinematic/slideshow/2907/grandstands/16847/7cf43338de33b36b2c52c388279135bb.jpg",
              "tribuna3": "Tribuna R + NFT - Vie, Sáb & Dom",
              "price3": "650",
              "img3": "https://static.tickets-platform.com/cinematic/slideshow/2907/grandstands/20627/d03378aa7895abdc3d41e0f1d9b88308.jpg"
            }
          }
        },
        {
          "season": "2023",
          "round": "21",
          "url": "https://es.wikipedia.org/wiki/Gran_Premio_de_Las_Vegas",
          "raceName": "Las Vegas Grand Prix",
          "Circuit": {
            "circuitId": "vegas",
            "url": "https://es.wikipedia.org/wiki/Circuito_callejero_de_Las_Vegas",
            "circuitName": "Las Vegas Strip Street Circuit",
            "Location": {
              "locality": "Las Vegas",
              "country": "USA / Las Vegas"
            },
            "Values": {
              "tribuna1": "SG1 - Vie, Sáb & Dom",
              "price1": "1300",
              "img1": "https://codigopoker.com/wp-content/uploads/2022/12/f1-caesars.png",
              "tribuna2": "SG2 - Vie, Sáb & Dom",
              "price2": "900",
              "img2": "https://sportsbase.io/images/gpfans/copy_1200x800/dd60054e7d9fc8c00199f6de57e6453631e5aabe.jpg"
            }
          }
        },
        {
          "season": "2023",
          "round": "22",
          "url": "https://es.wikipedia.org/wiki/Gran_Premio_de_Abu_Dabi",
          "raceName": "Abu Dhabi Grand Prix",
          "Circuit": {
            "circuitId": "yas_marina",
            "url": "https://es.wikipedia.org/wiki/Circuito_Yas_Marina",
            "circuitName": "Yas Marina Circuit",
            "Location": {
              "locality": "Abu Dhabi",
              "country": "Emiratos Arabes"
            },
            "Values": {
              "tribuna1": "Tribuna Marina - Orange Zone - Vie, Sáb & Dom",
              "price1": "650",
              "img1": "https://static.tickets-platform.com/cinematic/slideshow/51357/grandstands/9715/75c771f76e56cff4769c37fd5f708005.jpg",
              "tribuna2": "West Social Club - Vie, Sáb & Dom",
              "price2": "830",
              "img2": "https://static.tickets-platform.com/cinematic/slideshow/51357/grandstands/19687/23b9e8de6c404b3a01bd47f8961014be.jpg",
              "tribuna3": "North Straight Premium - Vie, Sáb & Dom",
              "price3": "950",
              "img3": "https://static.tickets-platform.com/cinematic/slideshow/51357/grandstands/21408/a5553a27b2c4d61ed9aa7fa706daba70.jpg"
            }
          }
        }
      ]
    }
  }
}
